milanlp/__init__.py
milanlp/milanlp.py
milanlp/cleaning/__init__.py
milanlp/cleaning/utilities.py
milanlp/twitter/__init__.py
milanlp/twitter/scraper.py
milanlp-0.1.0.dist-info/AUTHORS.rst
milanlp-0.1.0.dist-info/LICENSE
milanlp-0.1.0.dist-info/METADATA
milanlp-0.1.0.dist-info/WHEEL
milanlp-0.1.0.dist-info/top_level.txt
milanlp-0.1.0.dist-info/RECORD
